bitqt/__init__.py
bitqt/__main__.py
bitqt-0.0.2.dist-info/LICENSE
bitqt-0.0.2.dist-info/METADATA
bitqt-0.0.2.dist-info/WHEEL
bitqt-0.0.2.dist-info/entry_points.txt
bitqt-0.0.2.dist-info/top_level.txt
bitqt-0.0.2.dist-info/RECORD
