Metadata-Version: 2.1
Name: bitqt
Version: 0.0.2
Summary: A Graph-Based Approach to the  Quality Threshold Clustering of Molecular Dynamics
Home-page: https://github.com/LQCT/BitQT.git
Author: Roy Gonzalez-Aleman
Author-email: roy_gonzalez@fq.uh.cu
License: UNKNOWN
Platform: UNKNOWN
Classifier: Programming Language :: Python :: 3
Classifier: Programming Language :: Python :: 3.8
Requires-Dist: bitarray (>=1.6.1)
Requires-Dist: numpy
Requires-Dist: pandas
